pandasmore/__init__.py
pandasmore/_modidx.py
pandasmore/core.py
pandasmore-0.0.7.dist-info/licenses/LICENSE
pandasmore-0.0.7.dist-info/METADATA
pandasmore-0.0.7.dist-info/WHEEL
pandasmore-0.0.7.dist-info/entry_points.txt
pandasmore-0.0.7.dist-info/top_level.txt
pandasmore-0.0.7.dist-info/RECORD
